Workbook

Sheet README
A1: Wagamama challenger promo sizing template
A3: Purpose
A4: Forecast the gross and net cost of a lapsed-customer challenger promo for Wagamama customers after multi-aggregator launch. The template is pre-loaded with the cumulative target groups provided in the brief and uses editable assumptions for reach, redemption, funding, AOV, commission, and incrementality.
A6: How to use
A7: 1. Update blue cells in Inputs with the latest promo assumptions.
A8: 2. Update Target Groups if CRM sizing changes.
A9: 3. Use Scenario Builder to compare group size, voucher value, and low/base/high redemption cases.
A10: 4. Use Monthly Phasing to check whether each scenario fits the assumed monthly budget.
A11: 5. Use Sensitivity to stress-test one chosen audience and scenario across voucher values and redemption rates.
A14: Colour key
A15: Blue | B15: Editable input
A16: Grey | B16: Formula output
A17: Green | B17: Scenario or model guidance
A20: Google Sheets setup
A21: Option A: Upload this .xlsx to Google Drive, open with Google Sheets, then File > Save as Google Sheets.
A22: Option B: If you want an agent to create/update the native GSheet directly, enable a Google Sheets/Drive integration or provide a service-account/OAuth setup with spreadsheet and drive.file scopes, plus a destination folder or existing Sheet URL shared with that account.
A25: Important caveats
A26: Default redemption and incrementality values are placeholders for planning only.
A27: Costs are modelled as promotional discount funding plus comms and fixed costs. Update Inputs if restaurant funding or other cost sharing applies.
A28: Net cost after commission uses incremental orders only; if finance wants a different profitability lens, replace the contribution formula in Scenario Builder.

Sheet Inputs
A1: Editable assumptions
A2: Only edit blue cells. Scenario Builder and other output tabs update from these assumptions.
A4: Promo setup
A5: Promo length (months) | B5: 2 | C5: months | D5: Current thinking is a longer two-month challenger.
A6: Monthly budget available | B6: 250000 | C6: GBP | D6: Brief indicated an indicative 250k/month budget.
A7: Month 1 redemption weight | B7: 0.55 | C7: % of total | D7: Used by Monthly Phasing.
A8: Month 2 redemption weight | B8: 0.45 | C8: % of total | D8: Used by Monthly Phasing.
A9: Selected voucher value | B9: 7 | C9: GBP | D9: Primary mechanic for quick checks; scenario table also tests 5/7/10.
A10: Max claims per redeemer | B10: 1 | C10: orders | D10: Set >1 if the challenger allows multiple discounted orders.
A11: Deliveroo funding share | B11: 1 | C11: % | D11: Share of discount cost paid by Deliveroo/Rx marketing.
A12: Restaurant/partner funding share | B12: 0 | C12: % | D12: Information only unless finance wants to net this separately.
A13: Comms cost per targeted customer | B13: 0.03 | C13: GBP | D13: CRM, push, email or paid audience activation cost.
A14: Other fixed campaign costs | B14: 0 | C14: GBP | D14: Creative, tooling or agency costs.
A16: Commercial assumptions
A17: Average order value | B17: 25 | C17: GBP | D17: Use Wagamama AOV for the relevant lapsed cohort if available.
A18: Commission rate | B18: 0.3 | C18: % of AOV | D18: Use the new Wagamama commission rate.
A19: Variable cost to serve per order | B19: 0 | C19: GBP | D19: Optional fulfilment/support variable cost per incremental order.
A20: Baseline orders per reached customer | B20: 0.1 | C20: orders over promo period | D20: Used as a context metric, not in cost calculation.
A23: Scenario assumptions
A24: Assumption | B24: Low | C24: Base | D24: High | E24: Notes
A25: Reachable rate | B25: 0.75 | C25: 0.85 | D25: 0.9 | E25: Share of targetable customers who can be reached during the campaign.
A26: Redemption / completion rate | B26: 0.08 | C26: 0.15 | D26: 0.25 | E26: Share of reached customers who redeem or complete the challenger.
A27: Avg claims per redeemer | B27: 1 | C27: 1 | D27: 1.1 | E27: Average discounted orders per redeemer.
A28: Incrementality | B28: 0.35 | C28: 0.5 | D28: 0.65 | E28: Share of promo orders assumed incremental vs baseline/pulled-forward orders.
A31: Selected scenario controls
A32: Selected group for Sensitivity | B32: Medium
A33: Selected scenario for Sensitivity | B33: Base

Sheet Target Groups
A1: Cumulative target groups
A2: Customer counts are cumulative based on the Wagamama frequency-decline groups in the brief.
A4: Group option | B4: Definition | C4: Cumulative customers | D4: Incremental customers | E4: Recommended? | F4: Notes
A5: Tightest | B5: Habitual (3+ Wagamama orders) who fully lapsed | C5: 16209 | D5: =C5 | E5: No | F5: Smallest high-intent pool.
A6: Tight | B6: Tightest + habitual (3+) with >50% frequency decline | C6: 36746 | D6: =C6-C5 | E6: No | F6: Adds heavy decliners.
A7: Medium | B7: Tight + 2-order customers who lapsed | C7: 70821 | D7: =C7-C6 | E7: Minimum | F7: Brief indicated target up to Medium as a minimum.
A8: Broad | B8: Medium + habitual (3+) with 10-50% frequency decline | C8: 80431 | D8: =C8-C7 | E8: Size | F8: Marginal expansion from Medium.
A9: Widest | B9: Broad + lighter / one-time decliners | C9: 266280 | D9: =C9-C8 | E9: Size | F9: Largest pool; likely lower intent and lower redemption quality.

Sheet Scenario Builder
A1: Scenario Builder
A2: Compare cumulative audience groups, challenger voucher values, and low/base/high redemption assumptions.
A4: Group | B4: Target customers | C4: Voucher value | D4: Scenario | E4: Reachable rate | F4: Reached customers | G4: Redemption rate | H4: Redeemers | I4: Avg claims / redeemer | J4: Promo orders / claims | K4: Gross discount cost | L4: Deliveroo funded discount | M4: Comms cost | N4: Total investment | O4: Monthly investment | P4: Monthly budget gap/(headroom) | Q4: Baseline orders | R4: Incrementality | S4: Incremental orders | T4: Estimated commission contribution | U4: Variable cost | V4: Net cost after contribution | W4: Cost per incremental order
A5: Tightest | B5: =VLOOKUP(A5,'Target Groups'!$A$5:$C$9,3,FALSE) | C5: 5 | D5: Low | E5: =INDEX(Inputs!$B$25:$D$25,1,MATCH($D5,Inputs!$B$24:$D$24,0)) | F5: =B5*E5 | G5: =INDEX(Inputs!$B$26:$D$26,1,MATCH($D5,Inputs!$B$24:$D$24,0)) | H5: =F5*G5 | I5: =INDEX(Inputs!$B$27:$D$27,1,MATCH($D5,Inputs!$B$24:$D$24,0)) | J5: =H5*I5 | K5: =J5*C5 | L5: =K5*Inputs!$B$11 | M5: =B5*Inputs!$B$13 | N5: =L5+M5+Inputs!$B$14 | O5: =N5/Inputs!$B$5 | P5: =Inputs!$B$6-O5 | Q5: =F5*Inputs!$B$20 | R5: =INDEX(Inputs!$B$28:$D$28,1,MATCH($D5,Inputs!$B$24:$D$24,0)) | S5: =J5*R5 | T5: =S5*Inputs!$B$17*Inputs!$B$18 | U5: =S5*Inputs!$B$19 | V5: =N5-T5+U5 | W5: =IFERROR(V5/S5,"")
A6: Tightest | B6: =VLOOKUP(A6,'Target Groups'!$A$5:$C$9,3,FALSE) | C6: 5 | D6: Base | E6: =INDEX(Inputs!$B$25:$D$25,1,MATCH($D6,Inputs!$B$24:$D$24,0)) | F6: =B6*E6 | G6: =INDEX(Inputs!$B$26:$D$26,1,MATCH($D6,Inputs!$B$24:$D$24,0)) | H6: =F6*G6 | I6: =INDEX(Inputs!$B$27:$D$27,1,MATCH($D6,Inputs!$B$24:$D$24,0)) | J6: =H6*I6 | K6: =J6*C6 | L6: =K6*Inputs!$B$11 | M6: =B6*Inputs!$B$13 | N6: =L6+M6+Inputs!$B$14 | O6: =N6/Inputs!$B$5 | P6: =Inputs!$B$6-O6 | Q6: =F6*Inputs!$B$20 | R6: =INDEX(Inputs!$B$28:$D$28,1,MATCH($D6,Inputs!$B$24:$D$24,0)) | S6: =J6*R6 | T6: =S6*Inputs!$B$17*Inputs!$B$18 | U6: =S6*Inputs!$B$19 | V6: =N6-T6+U6 | W6: =IFERROR(V6/S6,"")
A7: Tightest | B7: =VLOOKUP(A7,'Target Groups'!$A$5:$C$9,3,FALSE) | C7: 5 | D7: High | E7: =INDEX(Inputs!$B$25:$D$25,1,MATCH($D7,Inputs!$B$24:$D$24,0)) | F7: =B7*E7 | G7: =INDEX(Inputs!$B$26:$D$26,1,MATCH($D7,Inputs!$B$24:$D$24,0)) | H7: =F7*G7 | I7: =INDEX(Inputs!$B$27:$D$27,1,MATCH($D7,Inputs!$B$24:$D$24,0)) | J7: =H7*I7 | K7: =J7*C7 | L7: =K7*Inputs!$B$11 | M7: =B7*Inputs!$B$13 | N7: =L7+M7+Inputs!$B$14 | O7: =N7/Inputs!$B$5 | P7: =Inputs!$B$6-O7 | Q7: =F7*Inputs!$B$20 | R7: =INDEX(Inputs!$B$28:$D$28,1,MATCH($D7,Inputs!$B$24:$D$24,0)) | S7: =J7*R7 | T7: =S7*Inputs!$B$17*Inputs!$B$18 | U7: =S7*Inputs!$B$19 | V7: =N7-T7+U7 | W7: =IFERROR(V7/S7,"")
A8: Tightest | B8: =VLOOKUP(A8,'Target Groups'!$A$5:$C$9,3,FALSE) | C8: 7 | D8: Low | E8: =INDEX(Inputs!$B$25:$D$25,1,MATCH($D8,Inputs!$B$24:$D$24,0)) | F8: =B8*E8 | G8: =INDEX(Inputs!$B$26:$D$26,1,MATCH($D8,Inputs!$B$24:$D$24,0)) | H8: =F8*G8 | I8: =INDEX(Inputs!$B$27:$D$27,1,MATCH($D8,Inputs!$B$24:$D$24,0)) | J8: =H8*I8 | K8: =J8*C8 | L8: =K8*Inputs!$B$11 | M8: =B8*Inputs!$B$13 | N8: =L8+M8+Inputs!$B$14 | O8: =N8/Inputs!$B$5 | P8: =Inputs!$B$6-O8 | Q8: =F8*Inputs!$B$20 | R8: =INDEX(Inputs!$B$28:$D$28,1,MATCH($D8,Inputs!$B$24:$D$24,0)) | S8: =J8*R8 | T8: =S8*Inputs!$B$17*Inputs!$B$18 | U8: =S8*Inputs!$B$19 | V8: =N8-T8+U8 | W8: =IFERROR(V8/S8,"")
A9: Tightest | B9: =VLOOKUP(A9,'Target Groups'!$A$5:$C$9,3,FALSE) | C9: 7 | D9: Base | E9: =INDEX(Inputs!$B$25:$D$25,1,MATCH($D9,Inputs!$B$24:$D$24,0)) | F9: =B9*E9 | G9: =INDEX(Inputs!$B$26:$D$26,1,MATCH($D9,Inputs!$B$24:$D$24,0)) | H9: =F9*G9 | I9: =INDEX(Inputs!$B$27:$D$27,1,MATCH($D9,Inputs!$B$24:$D$24,0)) | J9: =H9*I9 | K9: =J9*C9 | L9: =K9*Inputs!$B$11 | M9: =B9*Inputs!$B$13 | N9: =L9+M9+Inputs!$B$14 | O9: =N9/Inputs!$B$5 | P9: =Inputs!$B$6-O9 | Q9: =F9*Inputs!$B$20 | R9: =INDEX(Inputs!$B$28:$D$28,1,MATCH($D9,Inputs!$B$24:$D$24,0)) | S9: =J9*R9 | T9: =S9*Inputs!$B$17*Inputs!$B$18 | U9: =S9*Inputs!$B$19 | V9: =N9-T9+U9 | W9: =IFERROR(V9/S9,"")
A10: Tightest | B10: =VLOOKUP(A10,'Target Groups'!$A$5:$C$9,3,FALSE) | C10: 7 | D10: High | E10: =INDEX(Inputs!$B$25:$D$25,1,MATCH($D10,Inputs!$B$24:$D$24,0)) | F10: =B10*E10 | G10: =INDEX(Inputs!$B$26:$D$26,1,MATCH($D10,Inputs!$B$24:$D$24,0)) | H10: =F10*G10 | I10: =INDEX(Inputs!$B$27:$D$27,1,MATCH($D10,Inputs!$B$24:$D$24,0)) | J10: =H10*I10 | K10: =J10*C10 | L10: =K10*Inputs!$B$11 | M10: =B10*Inputs!$B$13 | N10: =L10+M10+Inputs!$B$14 | O10: =N10/Inputs!$B$5 | P10: =Inputs!$B$6-O10 | Q10: =F10*Inputs!$B$20 | R10: =INDEX(Inputs!$B$28:$D$28,1,MATCH($D10,Inputs!$B$24:$D$24,0)) | S10: =J10*R10 | T10: =S10*Inputs!$B$17*Inputs!$B$18 | U10: =S10*Inputs!$B$19 | V10: =N10-T10+U10 | W10: =IFERROR(V10/S10,"")
A11: Tightest | B11: =VLOOKUP(A11,'Target Groups'!$A$5:$C$9,3,FALSE) | C11: 10 | D11: Low | E11: =INDEX(Inputs!$B$25:$D$25,1,MATCH($D11,Inputs!$B$24:$D$24,0)) | F11: =B11*E11 | G11: =INDEX(Inputs!$B$26:$D$26,1,MATCH($D11,Inputs!$B$24:$D$24,0)) | H11: =F11*G11 | I11: =INDEX(Inputs!$B$27:$D$27,1,MATCH($D11,Inputs!$B$24:$D$24,0)) | J11: =H11*I11 | K11: =J11*C11 | L11: =K11*Inputs!$B$11 | M11: =B11*Inputs!$B$13 | N11: =L11+M11+Inputs!$B$14 | O11: =N11/Inputs!$B$5 | P11: =Inputs!$B$6-O11 | Q11: =F11*Inputs!$B$20 | R11: =INDEX(Inputs!$B$28:$D$28,1,MATCH($D11,Inputs!$B$24:$D$24,0)) | S11: =J11*R11 | T11: =S11*Inputs!$B$17*Inputs!$B$18 | U11: =S11*Inputs!$B$19 | V11: =N11-T11+U11 | W11: =IFERROR(V11/S11,"")
A12: Tightest | B12: =VLOOKUP(A12,'Target Groups'!$A$5:$C$9,3,FALSE) | C12: 10 | D12: Base | E12: =INDEX(Inputs!$B$25:$D$25,1,MATCH($D12,Inputs!$B$24:$D$24,0)) | F12: =B12*E12 | G12: =INDEX(Inputs!$B$26:$D$26,1,MATCH($D12,Inputs!$B$24:$D$24,0)) | H12: =F12*G12 | I12: =INDEX(Inputs!$B$27:$D$27,1,MATCH($D12,Inputs!$B$24:$D$24,0)) | J12: =H12*I12 | K12: =J12*C12 | L12: =K12*Inputs!$B$11 | M12: =B12*Inputs!$B$13 | N12: =L12+M12+Inputs!$B$14 | O12: =N12/Inputs!$B$5 | P12: =Inputs!$B$6-O12 | Q12: =F12*Inputs!$B$20 | R12: =INDEX(Inputs!$B$28:$D$28,1,MATCH($D12,Inputs!$B$24:$D$24,0)) | S12: =J12*R12 | T12: =S12*Inputs!$B$17*Inputs!$B$18 | U12: =S12*Inputs!$B$19 | V12: =N12-T12+U12 | W12: =IFERROR(V12/S12,"")
A13: Tightest | B13: =VLOOKUP(A13,'Target Groups'!$A$5:$C$9,3,FALSE) | C13: 10 | D13: High | E13: =INDEX(Inputs!$B$25:$D$25,1,MATCH($D13,Inputs!$B$24:$D$24,0)) | F13: =B13*E13 | G13: =INDEX(Inputs!$B$26:$D$26,1,MATCH($D13,Inputs!$B$24:$D$24,0)) | H13: =F13*G13 | I13: =INDEX(Inputs!$B$27:$D$27,1,MATCH($D13,Inputs!$B$24:$D$24,0)) | J13: =H13*I13 | K13: =J13*C13 | L13: =K13*Inputs!$B$11 | M13: =B13*Inputs!$B$13 | N13: =L13+M13+Inputs!$B$14 | O13: =N13/Inputs!$B$5 | P13: =Inputs!$B$6-O13 | Q13: =F13*Inputs!$B$20 | R13: =INDEX(Inputs!$B$28:$D$28,1,MATCH($D13,Inputs!$B$24:$D$24,0)) | S13: =J13*R13 | T13: =S13*Inputs!$B$17*Inputs!$B$18 | U13: =S13*Inputs!$B$19 | V13: =N13-T13+U13 | W13: =IFERROR(V13/S13,"")
A14: Tight | B14: =VLOOKUP(A14,'Target Groups'!$A$5:$C$9,3,FALSE) | C14: 5 | D14: Low | E14: =INDEX(Inputs!$B$25:$D$25,1,MATCH($D14,Inputs!$B$24:$D$24,0)) | F14: =B14*E14 | G14: =INDEX(Inputs!$B$26:$D$26,1,MATCH($D14,Inputs!$B$24:$D$24,0)) | H14: =F14*G14 | I14: =INDEX(Inputs!$B$27:$D$27,1,MATCH($D14,Inputs!$B$24:$D$24,0)) | J14: =H14*I14 | K14: =J14*C14 | L14: =K14*Inputs!$B$11 | M14: =B14*Inputs!$B$13 | N14: =L14+M14+Inputs!$B$14 | O14: =N14/Inputs!$B$5 | P14: =Inputs!$B$6-O14 | Q14: =F14*Inputs!$B$20 | R14: =INDEX(Inputs!$B$28:$D$28,1,MATCH($D14,Inputs!$B$24:$D$24,0)) | S14: =J14*R14 | T14: =S14*Inputs!$B$17*Inputs!$B$18 | U14: =S14*Inputs!$B$19 | V14: =N14-T14+U14 | W14: =IFERROR(V14/S14,"")
A15: Tight | B15: =VLOOKUP(A15,'Target Groups'!$A$5:$C$9,3,FALSE) | C15: 5 | D15: Base | E15: =INDEX(Inputs!$B$25:$D$25,1,MATCH($D15,Inputs!$B$24:$D$24,0)) | F15: =B15*E15 | G15: =INDEX(Inputs!$B$26:$D$26,1,MATCH($D15,Inputs!$B$24:$D$24,0)) | H15: =F15*G15 | I15: =INDEX(Inputs!$B$27:$D$27,1,MATCH($D15,Inputs!$B$24:$D$24,0)) | J15: =H15*I15 | K15: =J15*C15 | L15: =K15*Inputs!$B$11 | M15: =B15*Inputs!$B$13 | N15: =L15+M15+Inputs!$B$14 | O15: =N15/Inputs!$B$5 | P15: =Inputs!$B$6-O15 | Q15: =F15*Inputs!$B$20 | R15: =INDEX(Inputs!$B$28:$D$28,1,MATCH($D15,Inputs!$B$24:$D$24,0)) | S15: =J15*R15 | T15: =S15*Inputs!$B$17*Inputs!$B$18 | U15: =S15*Inputs!$B$19 | V15: =N15-T15+U15 | W15: =IFERROR(V15/S15,"")
A16: Tight | B16: =VLOOKUP(A16,'Target Groups'!$A$5:$C$9,3,FALSE) | C16: 5 | D16: High | E16: =INDEX(Inputs!$B$25:$D$25,1,MATCH($D16,Inputs!$B$24:$D$24,0)) | F16: =B16*E16 | G16: =INDEX(Inputs!$B$26:$D$26,1,MATCH($D16,Inputs!$B$24:$D$24,0)) | H16: =F16*G16 | I16: =INDEX(Inputs!$B$27:$D$27,1,MATCH($D16,Inputs!$B$24:$D$24,0)) | J16: =H16*I16 | K16: =J16*C16 | L16: =K16*Inputs!$B$11 | M16: =B16*Inputs!$B$13 | N16: =L16+M16+Inputs!$B$14 | O16: =N16/Inputs!$B$5 | P16: =Inputs!$B$6-O16 | Q16: =F16*Inputs!$B$20 | R16: =INDEX(Inputs!$B$28:$D$28,1,MATCH($D16,Inputs!$B$24:$D$24,0)) | S16: =J16*R16 | T16: =S16*Inputs!$B$17*Inputs!$B$18 | U16: =S16*Inputs!$B$19 | V16: =N16-T16+U16 | W16: =IFERROR(V16/S16,"")
... A49: Widest | B49: =VLOOKUP(A49,'Target Groups'!$A$5:$C$9,3,FALSE) | C49: 10 | D49: High | E49: =INDEX(Inputs!$B$25:$D$25,1,MATCH($D49,Inputs!$B$24:$D$24,0)) | F49: =B49*E49 | G49: =INDEX(Inputs!$B$26:$D$26,1,MATCH($D49,Inputs!$B$24:$D$24,0)) | H49: =F49*G49 | I49: =INDEX(Inputs!$B$27:$D$27,1,MATCH($D49,Inputs!$B$24:$D$24,0)) | J49: =H49*I49 | K49: =J49*C49 | L49: =K49*Inputs!$B$11 | M49: =B49*Inputs!$B$13 | N49: =L49+M49+Inputs!$B$14 | O49: =N49/Inputs!$B$5 | P49: =Inputs!$B$6-O49 | Q49: =F49*Inputs!$B$20 | R49: =INDEX(Inputs!$B$28:$D$28,1,MATCH($D49,Inputs!$B$24:$D$24,0)) | S49: =J49*R49 | T49: =S49*Inputs!$B$17*Inputs!$B$18 | U49: =S49*Inputs!$B$19 | V49: =N49-T49+U49 | W49: =IFERROR(V49/S49,"")

Sheet Monthly Phasing
A1: Monthly Phasing
A2: Two-month spend phasing from Inputs. Negative monthly headroom indicates a budget gap.
A4: Group | B4: Voucher value | C4: Scenario | D4: Total investment | E4: Month 1 weight | F4: Month 1 cost | G4: Month 1 headroom | H4: Month 2 weight | I4: Month 2 cost | J4: Month 2 headroom
A5: Medium | B5: 5 | C5: Low | D5: =SUMIFS('Scenario Builder'!$N$5:$N$49,'Scenario Builder'!$A$5:$A$49,A5,'Scenario Builder'!$C$5:$C$49,B5,'Scenario Builder'!$D$5:$D$49,C5) | E5: =Inputs!$B$7 | F5: =D5*E5 | G5: =Inputs!$B$6-F5 | H5: =Inputs!$B$8 | I5: =D5*H5 | J5: =Inputs!$B$6-I5
A6: Medium | B6: 5 | C6: Base | D6: =SUMIFS('Scenario Builder'!$N$5:$N$49,'Scenario Builder'!$A$5:$A$49,A6,'Scenario Builder'!$C$5:$C$49,B6,'Scenario Builder'!$D$5:$D$49,C6) | E6: =Inputs!$B$7 | F6: =D6*E6 | G6: =Inputs!$B$6-F6 | H6: =Inputs!$B$8 | I6: =D6*H6 | J6: =Inputs!$B$6-I6
A7: Medium | B7: 5 | C7: High | D7: =SUMIFS('Scenario Builder'!$N$5:$N$49,'Scenario Builder'!$A$5:$A$49,A7,'Scenario Builder'!$C$5:$C$49,B7,'Scenario Builder'!$D$5:$D$49,C7) | E7: =Inputs!$B$7 | F7: =D7*E7 | G7: =Inputs!$B$6-F7 | H7: =Inputs!$B$8 | I7: =D7*H7 | J7: =Inputs!$B$6-I7
A8: Medium | B8: 7 | C8: Low | D8: =SUMIFS('Scenario Builder'!$N$5:$N$49,'Scenario Builder'!$A$5:$A$49,A8,'Scenario Builder'!$C$5:$C$49,B8,'Scenario Builder'!$D$5:$D$49,C8) | E8: =Inputs!$B$7 | F8: =D8*E8 | G8: =Inputs!$B$6-F8 | H8: =Inputs!$B$8 | I8: =D8*H8 | J8: =Inputs!$B$6-I8
A9: Medium | B9: 7 | C9: Base | D9: =SUMIFS('Scenario Builder'!$N$5:$N$49,'Scenario Builder'!$A$5:$A$49,A9,'Scenario Builder'!$C$5:$C$49,B9,'Scenario Builder'!$D$5:$D$49,C9) | E9: =Inputs!$B$7 | F9: =D9*E9 | G9: =Inputs!$B$6-F9 | H9: =Inputs!$B$8 | I9: =D9*H9 | J9: =Inputs!$B$6-I9
A10: Medium | B10: 7 | C10: High | D10: =SUMIFS('Scenario Builder'!$N$5:$N$49,'Scenario Builder'!$A$5:$A$49,A10,'Scenario Builder'!$C$5:$C$49,B10,'Scenario Builder'!$D$5:$D$49,C10) | E10: =Inputs!$B$7 | F10: =D10*E10 | G10: =Inputs!$B$6-F10 | H10: =Inputs!$B$8 | I10: =D10*H10 | J10: =Inputs!$B$6-I10
A11: Medium | B11: 10 | C11: Low | D11: =SUMIFS('Scenario Builder'!$N$5:$N$49,'Scenario Builder'!$A$5:$A$49,A11,'Scenario Builder'!$C$5:$C$49,B11,'Scenario Builder'!$D$5:$D$49,C11) | E11: =Inputs!$B$7 | F11: =D11*E11 | G11: =Inputs!$B$6-F11 | H11: =Inputs!$B$8 | I11: =D11*H11 | J11: =Inputs!$B$6-I11
A12: Medium | B12: 10 | C12: Base | D12: =SUMIFS('Scenario Builder'!$N$5:$N$49,'Scenario Builder'!$A$5:$A$49,A12,'Scenario Builder'!$C$5:$C$49,B12,'Scenario Builder'!$D$5:$D$49,C12) | E12: =Inputs!$B$7 | F12: =D12*E12 | G12: =Inputs!$B$6-F12 | H12: =Inputs!$B$8 | I12: =D12*H12 | J12: =Inputs!$B$6-I12
A13: Medium | B13: 10 | C13: High | D13: =SUMIFS('Scenario Builder'!$N$5:$N$49,'Scenario Builder'!$A$5:$A$49,A13,'Scenario Builder'!$C$5:$C$49,B13,'Scenario Builder'!$D$5:$D$49,C13) | E13: =Inputs!$B$7 | F13: =D13*E13 | G13: =Inputs!$B$6-F13 | H13: =Inputs!$B$8 | I13: =D13*H13 | J13: =Inputs!$B$6-I13
A14: Broad | B14: 5 | C14: Low | D14: =SUMIFS('Scenario Builder'!$N$5:$N$49,'Scenario Builder'!$A$5:$A$49,A14,'Scenario Builder'!$C$5:$C$49,B14,'Scenario Builder'!$D$5:$D$49,C14) | E14: =Inputs!$B$7 | F14: =D14*E14 | G14: =Inputs!$B$6-F14 | H14: =Inputs!$B$8 | I14: =D14*H14 | J14: =Inputs!$B$6-I14
A15: Broad | B15: 5 | C15: Base | D15: =SUMIFS('Scenario Builder'!$N$5:$N$49,'Scenario Builder'!$A$5:$A$49,A15,'Scenario Builder'!$C$5:$C$49,B15,'Scenario Builder'!$D$5:$D$49,C15) | E15: =Inputs!$B$7 | F15: =D15*E15 | G15: =Inputs!$B$6-F15 | H15: =Inputs!$B$8 | I15: =D15*H15 | J15: =Inputs!$B$6-I15
A16: Broad | B16: 5 | C16: High | D16: =SUMIFS('Scenario Builder'!$N$5:$N$49,'Scenario Builder'!$A$5:$A$49,A16,'Scenario Builder'!$C$5:$C$49,B16,'Scenario Builder'!$D$5:$D$49,C16) | E16: =Inputs!$B$7 | F16: =D16*E16 | G16: =Inputs!$B$6-F16 | H16: =Inputs!$B$8 | I16: =D16*H16 | J16: =Inputs!$B$6-I16
... A31: Widest | B31: 10 | C31: High | D31: =SUMIFS('Scenario Builder'!$N$5:$N$49,'Scenario Builder'!$A$5:$A$49,A31,'Scenario Builder'!$C$5:$C$49,B31,'Scenario Builder'!$D$5:$D$49,C31) | E31: =Inputs!$B$7 | F31: =D31*E31 | G31: =Inputs!$B$6-F31 | H31: =Inputs!$B$8 | I31: =D31*H31 | J31: =Inputs!$B$6-I31

Sheet Sensitivity
A1: Sensitivity
A2: Stress-test total investment and net cost for the selected group/scenario in Inputs.
A4: Selected group | B4: =Inputs!$B$32
A5: Selected scenario | B5: =Inputs!$B$33
A6: Target customers | B6: =VLOOKUP(B4,'Target Groups'!$A$5:$C$9,3,FALSE)
A7: Reachable rate | B7: =INDEX(Inputs!$B$25:$D$25,1,MATCH(B5,Inputs!$B$24:$D$24,0))
A8: Avg claims / redeemer | B8: =INDEX(Inputs!$B$27:$D$27,1,MATCH(B5,Inputs!$B$24:$D$24,0))
A9: Incrementality | B9: =INDEX(Inputs!$B$28:$D$28,1,MATCH(B5,Inputs!$B$24:$D$24,0))
A12: Total investment by voucher value and redemption rate
A14: Voucher value | B14: 0.05 | C14: 0.08 | D14: 0.1 | E14: 0.15 | F14: 0.2 | G14: 0.25 | H14: 0.3
A15: 5 | B15: =($B$6*$B$7*B$14*$B$8*$A15*Inputs!$B$11)+($B$6*Inputs!$B$13)+Inputs!$B$14 | C15: =($B$6*$B$7*C$14*$B$8*$A15*Inputs!$B$11)+($B$6*Inputs!$B$13)+Inputs!$B$14 | D15: =($B$6*$B$7*D$14*$B$8*$A15*Inputs!$B$11)+($B$6*Inputs!$B$13)+Inputs!$B$14 | E15: =($B$6*$B$7*E$14*$B$8*$A15*Inputs!$B$11)+($B$6*Inputs!$B$13)+Inputs!$B$14 | F15: =($B$6*$B$7*F$14*$B$8*$A15*Inputs!$B$11)+($B$6*Inputs!$B$13)+Inputs!$B$14 | G15: =($B$6*$B$7*G$14*$B$8*$A15*Inputs!$B$11)+($B$6*Inputs!$B$13)+Inputs!$B$14 | H15: =($B$6*$B$7*H$14*$B$8*$A15*Inputs!$B$11)+($B$6*Inputs!$B$13)+Inputs!$B$14
A16: 7 | B16: =($B$6*$B$7*B$14*$B$8*$A16*Inputs!$B$11)+($B$6*Inputs!$B$13)+Inputs!$B$14 | C16: =($B$6*$B$7*C$14*$B$8*$A16*Inputs!$B$11)+($B$6*Inputs!$B$13)+Inputs!$B$14 | D16: =($B$6*$B$7*D$14*$B$8*$A16*Inputs!$B$11)+($B$6*Inputs!$B$13)+Inputs!$B$14 | E16: =($B$6*$B$7*E$14*$B$8*$A16*Inputs!$B$11)+($B$6*Inputs!$B$13)+Inputs!$B$14 | F16: =($B$6*$B$7*F$14*$B$8*$A16*Inputs!$B$11)+($B$6*Inputs!$B$13)+Inputs!$B$14 | G16: =($B$6*$B$7*G$14*$B$8*$A16*Inputs!$B$11)+($B$6*Inputs!$B$13)+Inputs!$B$14 | H16: =($B$6*$B$7*H$14*$B$8*$A16*Inputs!$B$11)+($B$6*Inputs!$B$13)+Inputs!$B$14
A17: 10 | B17: =($B$6*$B$7*B$14*$B$8*$A17*Inputs!$B$11)+($B$6*Inputs!$B$13)+Inputs!$B$14 | C17: =($B$6*$B$7*C$14*$B$8*$A17*Inputs!$B$11)+($B$6*Inputs!$B$13)+Inputs!$B$14 | D17: =($B$6*$B$7*D$14*$B$8*$A17*Inputs!$B$11)+($B$6*Inputs!$B$13)+Inputs!$B$14 | E17: =($B$6*$B$7*E$14*$B$8*$A17*Inputs!$B$11)+($B$6*Inputs!$B$13)+Inputs!$B$14 | F17: =($B$6*$B$7*F$14*$B$8*$A17*Inputs!$B$11)+($B$6*Inputs!$B$13)+Inputs!$B$14 | G17: =($B$6*$B$7*G$14*$B$8*$A17*Inputs!$B$11)+($B$6*Inputs!$B$13)+Inputs!$B$14 | H17: =($B$6*$B$7*H$14*$B$8*$A17*Inputs!$B$11)+($B$6*Inputs!$B$13)+Inputs!$B$14
A20: Net cost after contribution by voucher value and redemption rate
A22: Voucher value | B22: 0.05 | C22: 0.08 | D22: 0.1 | E22: 0.15 | F22: 0.2 | G22: 0.25 | H22: 0.3
A23: 5 | B23: =B15-(($B$6*$B$7*B$22*$B$8*$B$9)*Inputs!$B$17*Inputs!$B$18)+(($B$6*$B$7*B$22*$B$8*$B$9)*Inputs!$B$19) | C23: =C15-(($B$6*$B$7*C$22*$B$8*$B$9)*Inputs!$B$17*Inputs!$B$18)+(($B$6*$B$7*C$22*$B$8*$B$9)*Inputs!$B$19) | D23: =D15-(($B$6*$B$7*D$22*$B$8*$B$9)*Inputs!$B$17*Inputs!$B$18)+(($B$6*$B$7*D$22*$B$8*$B$9)*Inputs!$B$19) | E23: =E15-(($B$6*$B$7*E$22*$B$8*$B$9)*Inputs!$B$17*Inputs!$B$18)+(($B$6*$B$7*E$22*$B$8*$B$9)*Inputs!$B$19) | F23: =F15-(($B$6*$B$7*F$22*$B$8*$B$9)*Inputs!$B$17*Inputs!$B$18)+(($B$6*$B$7*F$22*$B$8*$B$9)*Inputs!$B$19) | G23: =G15-(($B$6*$B$7*G$22*$B$8*$B$9)*Inputs!$B$17*Inputs!$B$18)+(($B$6*$B$7*G$22*$B$8*$B$9)*Inputs!$B$19) | H23: =H15-(($B$6*$B$7*H$22*$B$8*$B$9)*Inputs!$B$17*Inputs!$B$18)+(($B$6*$B$7*H$22*$B$8*$B$9)*Inputs!$B$19)
A24: 7 | B24: =B16-(($B$6*$B$7*B$22*$B$8*$B$9)*Inputs!$B$17*Inputs!$B$18)+(($B$6*$B$7*B$22*$B$8*$B$9)*Inputs!$B$19) | C24: =C16-(($B$6*$B$7*C$22*$B$8*$B$9)*Inputs!$B$17*Inputs!$B$18)+(($B$6*$B$7*C$22*$B$8*$B$9)*Inputs!$B$19) | D24: =D16-(($B$6*$B$7*D$22*$B$8*$B$9)*Inputs!$B$17*Inputs!$B$18)+(($B$6*$B$7*D$22*$B$8*$B$9)*Inputs!$B$19) | E24: =E16-(($B$6*$B$7*E$22*$B$8*$B$9)*Inputs!$B$17*Inputs!$B$18)+(($B$6*$B$7*E$22*$B$8*$B$9)*Inputs!$B$19) | F24: =F16-(($B$6*$B$7*F$22*$B$8*$B$9)*Inputs!$B$17*Inputs!$B$18)+(($B$6*$B$7*F$22*$B$8*$B$9)*Inputs!$B$19) | G24: =G16-(($B$6*$B$7*G$22*$B$8*$B$9)*Inputs!$B$17*Inputs!$B$18)+(($B$6*$B$7*G$22*$B$8*$B$9)*Inputs!$B$19) | H24: =H16-(($B$6*$B$7*H$22*$B$8*$B$9)*Inputs!$B$17*Inputs!$B$18)+(($B$6*$B$7*H$22*$B$8*$B$9)*Inputs!$B$19)
A25: 10 | B25: =B17-(($B$6*$B$7*B$22*$B$8*$B$9)*Inputs!$B$17*Inputs!$B$18)+(($B$6*$B$7*B$22*$B$8*$B$9)*Inputs!$B$19) | C25: =C17-(($B$6*$B$7*C$22*$B$8*$B$9)*Inputs!$B$17*Inputs!$B$18)+(($B$6*$B$7*C$22*$B$8*$B$9)*Inputs!$B$19) | D25: =D17-(($B$6*$B$7*D$22*$B$8*$B$9)*Inputs!$B$17*Inputs!$B$18)+(($B$6*$B$7*D$22*$B$8*$B$9)*Inputs!$B$19) | E25: =E17-(($B$6*$B$7*E$22*$B$8*$B$9)*Inputs!$B$17*Inputs!$B$18)+(($B$6*$B$7*E$22*$B$8*$B$9)*Inputs!$B$19) | F25: =F17-(($B$6*$B$7*F$22*$B$8*$B$9)*Inputs!$B$17*Inputs!$B$18)+(($B$6*$B$7*F$22*$B$8*$B$9)*Inputs!$B$19) | G25: =G17-(($B$6*$B$7*G$22*$B$8*$B$9)*Inputs!$B$17*Inputs!$B$18)+(($B$6*$B$7*G$22*$B$8*$B$9)*Inputs!$B$19) | H25: =H17-(($B$6*$B$7*H$22*$B$8*$B$9)*Inputs!$B$17*Inputs!$B$18)+(($B$6*$B$7*H$22*$B$8*$B$9)*Inputs!$B$19)
